divide_and_cover/__init__.py
divide_and_cover/__main__.py
divide_and_cover/coverage_handler.py
divide_and_cover-0.7.3.dist-info/METADATA
divide_and_cover-0.7.3.dist-info/RECORD
divide_and_cover-0.7.3.dist-info/WHEEL
divide_and_cover-0.7.3.dist-info/top_level.txt
