Metadata-Version: 2.1
Name: divide-and-cover
Version: 0.7.3
Summary: Picky test coverage runner
Home-page: UNKNOWN
Author: Max Woerner Chase
Author-email: max.chase@gmail.com
License: MIT
Keywords: coverage
Platform: UNKNOWN
Classifier: Development Status :: 7 - Inactive
Classifier: License :: OSI Approved :: MIT License
Classifier: Programming Language :: Python :: 3
Classifier: Programming Language :: Python :: 3.6
Requires-Dist: coverage (<4.6,>=4.5)
